cool/__init__.py
cool/__version__.py
cool/partial.py
cool/pipe.py
cool/redirect.py
cool-0.4.0.dist-info/LICENSE
cool-0.4.0.dist-info/WHEEL
cool-0.4.0.dist-info/METADATA
cool-0.4.0.dist-info/RECORD
